{
	"_embedded": {
		"_entries": [
			{
				"kode": "user",
				"navn": "User based license",
				"systemid": {
					"identifikatorverdi": "1"
				},
				"_links": {
					"self": [
						{
							"href": "https://beta.felleskomponent.no/eiendeler/kodeverk/lisenstype/systemid/1"
						}
					]
				}
			},
			{
				"kode": "device",
				"navn": "Device based license",
				"systemid": {
					"identifikatorverdi": "2"
				},
				"_links": {
					"self": [
						{
							"href": "https://beta.felleskomponent.no/eiendeler/kodeverk/lisenstype/systemid/2"
						}
					]
				}
			},
			{
				"kode": "site",
				"navn": "Site license",
				"systemid": {
					"identifikatorverdi": "3"
				},
				"_links": {
					"self": [
						{
							"href": "https://beta.felleskomponent.no/eiendeler/kodeverk/lisenstype/systemid/3"
						}
					]
				}
			}			
		]			
	},
	"_links": {
		"self": [
			{
				"href": "https://beta.felleskomponent.no/eiendeler/kodeverk/lisenstype/"
			}
		]
	},
	"total_items": 3
}